LICENSE
MANIFEST.in
README.md
setup.py
Math/DeterminantZero.py
Math/DiscreteDistribution.c
Math/DiscreteDistribution.pxd
Math/DiscreteDistribution.pyx
Math/Distribution.c
Math/Distribution.pxd
Math/Distribution.pyx
Math/Eigenvector.c
Math/Eigenvector.pxd
Math/Eigenvector.pyx
Math/Matrix.c
Math/Matrix.pxd
Math/Matrix.pyx
Math/MatrixColumnMismatch.py
Math/MatrixDimensionMismatch.py
Math/MatrixNotPositiveDefinite.py
Math/MatrixNotSquare.py
Math/MatrixNotSymmetric.py
Math/MatrixRowColumnMismatch.py
Math/MatrixRowMismatch.py
Math/Tensor.c
Math/Tensor.pxd
Math/Tensor.pyx
Math/Vector.c
Math/Vector.pxd
Math/Vector.pyx
Math/VectorSizeMismatch.py
Math/__init__.py
NlpToolkit_Math_Cy.egg-info/PKG-INFO
NlpToolkit_Math_Cy.egg-info/SOURCES.txt
NlpToolkit_Math_Cy.egg-info/dependency_links.txt
NlpToolkit_Math_Cy.egg-info/top_level.txt
nlptoolkit_math_cy.egg-info/PKG-INFO
nlptoolkit_math_cy.egg-info/SOURCES.txt
nlptoolkit_math_cy.egg-info/dependency_links.txt
nlptoolkit_math_cy.egg-info/top_level.txt