Metadata-Version: 2.1
Name: nlptoolkit-math-cy
Version: 1.0.17
Summary: Math library
Home-page: https://github.com/StarlangSoftware/Math-Cy
Author: olcaytaner
Author-email: olcay.yildiz@ozyegin.edu.tr
License: UNKNOWN
Platform: UNKNOWN
